ptee.py
ptee-0.4.1.dist-info/LICENSE.rst
ptee-0.4.1.dist-info/METADATA
ptee-0.4.1.dist-info/WHEEL
ptee-0.4.1.dist-info/entry_points.txt
ptee-0.4.1.dist-info/top_level.txt
ptee-0.4.1.dist-info/zip-safe
ptee-0.4.1.dist-info/RECORD
