Metadata-Version: 2.1
Name: ptee
Version: 0.4.1
Summary: "Progress tee", an enhanced "tee" program with in-place overwriting of "status".
Home-page: https://github.com/drmikehenry/ptee
Author: Michael Henry
Author-email: drmikehenry@drmikehenry.com
License: MIT
Keywords: progress tee in-place overwriting status
Platform: UNKNOWN
Classifier: Development Status :: 5 - Production/Stable
Classifier: Topic :: Text Processing :: Filters
Classifier: Topic :: Utilities
Classifier: Environment :: Console
Classifier: License :: OSI Approved :: MIT License
Classifier: Programming Language :: Python :: 3 :: Only
Classifier: Programming Language :: Python :: 3
Classifier: Programming Language :: Python :: 3.5
Classifier: Programming Language :: Python :: 3.6
Classifier: Programming Language :: Python :: 3.7
Classifier: Programming Language :: Python :: 3.8
Requires-Python: >=3.5
Requires-Dist: blessed (==1.17.0)
Requires-Dist: six (==1.14.0)
Requires-Dist: wcwidth (==0.1.8)
Provides-Extra: dev
Requires-Dist: attrs (==19.3.0) ; extra == 'dev'
Requires-Dist: coverage (==5.0.3) ; extra == 'dev'
Requires-Dist: entrypoints (==0.3) ; extra == 'dev'
Requires-Dist: flake8-import-order (==0.18.1) ; extra == 'dev'
Requires-Dist: flake8-polyfill (==1.0.2) ; extra == 'dev'
Requires-Dist: flake8-quotes (==2.1.1) ; extra == 'dev'
Requires-Dist: flake8 (==3.7.9) ; extra == 'dev'
Requires-Dist: importlib-metadata (==1.4.0) ; extra == 'dev'
Requires-Dist: mccabe (==0.6.1) ; extra == 'dev'
Requires-Dist: more-itertools (==8.1.0) ; extra == 'dev'
Requires-Dist: mypy-extensions (==0.4.3) ; extra == 'dev'
Requires-Dist: mypy (==0.761) ; extra == 'dev'
Requires-Dist: packaging (==20.0) ; extra == 'dev'
Requires-Dist: pep8-naming (==0.9.1) ; extra == 'dev'
Requires-Dist: pluggy (==0.13.1) ; extra == 'dev'
Requires-Dist: py (==1.8.1) ; extra == 'dev'
Requires-Dist: pycodestyle (==2.5.0) ; extra == 'dev'
Requires-Dist: pyflakes (==2.1.1) ; extra == 'dev'
Requires-Dist: pyparsing (==2.4.6) ; extra == 'dev'
Requires-Dist: pytest-cov (==2.8.1) ; extra == 'dev'
Requires-Dist: pytest (==5.3.3) ; extra == 'dev'
Requires-Dist: six (==1.14.0) ; extra == 'dev'
Requires-Dist: typed-ast (==1.4.1) ; extra == 'dev'
Requires-Dist: typing-extensions (==3.7.4.1) ; extra == 'dev'
Requires-Dist: wcwidth (==0.1.8) ; extra == 'dev'
Requires-Dist: zipp (==1.0.0) ; extra == 'dev'
